tests/__init__.py
tests/test_treeprinter.py
treeprinter/__init__.py
treeprinter/binaryTreeprinter.py
treeprinter_le99-0.0.3.dist-info/LICENSE
treeprinter_le99-0.0.3.dist-info/METADATA
treeprinter_le99-0.0.3.dist-info/WHEEL
treeprinter_le99-0.0.3.dist-info/top_level.txt
treeprinter_le99-0.0.3.dist-info/RECORD
